deeptuner/__init__.py
deeptuner/siamese_network.py
deeptuner/tripletdatagenerator.py
deeptuner/utils.py
deeptuner/architectures/__init__.py
deeptuner/architectures/siamese.py
deeptuner/backbones/__init__.py
deeptuner/backbones/efficientnet.py
deeptuner/backbones/mobilenet.py
deeptuner/backbones/resnet.py
deeptuner/callbacks/__init__.py
deeptuner/callbacks/finetune_callback.py
deeptuner/datagenerators/__init__.py
deeptuner/datagenerators/arcface_generator.py
deeptuner/datagenerators/triplet_data_generator.py
deeptuner/losses/__init__.py
deeptuner/losses/arcface_loss.py
deeptuner/losses/center_loss.py
deeptuner/losses/contrastive_loss.py
deeptuner/losses/npair_loss.py
deeptuner/losses/triplet_loss.py
deeptuner/utils/__init__.py
deeptuner/utils/helpers.py
deeptuner-0.2.0.dist-info/LICENSE
deeptuner-0.2.0.dist-info/METADATA
deeptuner-0.2.0.dist-info/WHEEL
deeptuner-0.2.0.dist-info/top_level.txt
deeptuner-0.2.0.dist-info/RECORD
