Metadata-Version: 2.1
Name: deeptuner
Version: 0.2.0
Summary: A package for fine-tuning deep learning models with Siamese architecture and triplet loss
Home-page: https://github.com/Devasy23/DeepTuner
Author: Devasy Patel
Author-email: patel.devasy.23@gmail.com
License: UNKNOWN
Platform: UNKNOWN
Classifier: Development Status :: 3 - Alpha
Classifier: Intended Audience :: Developers
Classifier: Intended Audience :: Science/Research
Classifier: License :: OSI Approved :: BSD License
Classifier: Programming Language :: Python :: 3
Classifier: Programming Language :: Python :: 3.7
Classifier: Programming Language :: Python :: 3.8
Classifier: Programming Language :: Python :: 3.9
Classifier: Programming Language :: Python :: 3.10
Classifier: Topic :: Scientific/Engineering :: Artificial Intelligence
Requires-Python: >=3.7
License-File: LICENSE
Requires-Dist: tensorflow>=2.12.0
Requires-Dist: numpy>=1.21.0
Requires-Dist: scikit-learn>=1.0.0
Requires-Dist: Pillow>=9.0.0
Requires-Dist: wandb>=0.15.0
Requires-Dist: efficientnet>=1.0.0
Requires-Dist: facenet-pytorch>=2.5.0
Requires-Dist: requests>=2.31.0
Requires-Dist: tqdm>=4.65.0
